coop_html_editor/__init__.py
coop_html_editor/apps.py
coop_html_editor/forms.py
coop_html_editor/settings.py
coop_html_editor/urls.py
coop_html_editor/utils.py
coop_html_editor/views.py
coop_html_editor/widgets.py
coop_html_editor/locale/fr/LC_MESSAGES/django.mo
coop_html_editor/locale/fr/LC_MESSAGES/django.po
coop_html_editor/static/ckeditor.4.6.2/CHANGES.md
coop_html_editor/static/ckeditor.4.6.2/LICENSE.md
coop_html_editor/static/ckeditor.4.6.2/README.md
coop_html_editor/static/ckeditor.4.6.2/build-config.js
coop_html_editor/static/ckeditor.4.6.2/ckeditor.js
coop_html_editor/static/ckeditor.4.6.2/config.js
coop_html_editor/static/ckeditor.4.6.2/contents.css
coop_html_editor/static/ckeditor.4.6.2/styles.js
coop_html_editor/static/ckeditor.4.6.2/adapters/jquery.js
coop_html_editor/static/ckeditor.4.6.2/lang/en.js
coop_html_editor/static/ckeditor.4.6.2/lang/fr.js
coop_html_editor/static/ckeditor.4.6.2/plugins/icons.png
coop_html_editor/static/ckeditor.4.6.2/plugins/icons_hidpi.png
coop_html_editor/static/ckeditor.4.6.2/plugins/a11yhelp/dialogs/a11yhelp.js
coop_html_editor/static/ckeditor.4.6.2/plugins/a11yhelp/dialogs/lang/_translationstatus.txt
coop_html_editor/static/ckeditor.4.6.2/plugins/a11yhelp/dialogs/lang/af.js
coop_html_editor/static/ckeditor.4.6.2/plugins/a11yhelp/dialogs/lang/ar.js
coop_html_editor/static/ckeditor.4.6.2/plugins/a11yhelp/dialogs/lang/az.js
coop_html_editor/static/ckeditor.4.6.2/plugins/a11yhelp/dialogs/lang/bg.js
coop_html_editor/static/ckeditor.4.6.2/plugins/a11yhelp/dialogs/lang/ca.js
coop_html_editor/static/ckeditor.4.6.2/plugins/a11yhelp/dialogs/lang/cs.js
coop_html_editor/static/ckeditor.4.6.2/plugins/a11yhelp/dialogs/lang/cy.js
coop_html_editor/static/ckeditor.4.6.2/plugins/a11yhelp/dialogs/lang/da.js
coop_html_editor/static/ckeditor.4.6.2/plugins/a11yhelp/dialogs/lang/de-ch.js
coop_html_editor/static/ckeditor.4.6.2/plugins/a11yhelp/dialogs/lang/de.js
coop_html_editor/static/ckeditor.4.6.2/plugins/a11yhelp/dialogs/lang/el.js
coop_html_editor-1.4.1.dist-info/METADATA
coop_html_editor-1.4.1.dist-info/WHEEL
coop_html_editor-1.4.1.dist-info/top_level.txt
coop_html_editor-1.4.1.dist-info/RECORD
