Metadata-Version: 2.1
Name: coop-html-editor
Version: 1.4.1
Summary: integration for Inline HTML editor
Home-page: https://github.com/ljean/coop_html_editor/
Download-URL: https://github.com/ljean/coop_html_editor/tarball/master
Author: Luc Jean
Author-email: ljean@apidev.fr
License: BSD
Requires-Dist: apidev-django-floppyforms
